jkepler/__init__.py
jkepler/jkepler_version.py
jkepler/astrometry/__init__.py
jkepler/astrometry/astrometry.py
jkepler/data/__init__.py
jkepler/data/tests/kic11773022_koiinfo.csv
jkepler/data/tests/kic11773022_long_transits.csv
jkepler/data/tests/mann19_astrometry.txt
jkepler/data/tests/mann19_orbit.txt
jkepler/data/tests/v723mon_s12_rv.csv
jkepler/kepler/__init__.py
jkepler/kepler/kepler.py
jkepler/kepler/markley.py
jkepler/rv/__init__.py
jkepler/rv/rv.py
jkepler/tests/__init__.py
jkepler/tests/read_testdata.py
jkepler/transit/__init__.py
jkepler/transit/transit.py
jkepler/transit/transitfit.py
jkepler-0.1.0.dist-info/LICENSE
jkepler-0.1.0.dist-info/METADATA
jkepler-0.1.0.dist-info/WHEEL
jkepler-0.1.0.dist-info/top_level.txt
jkepler-0.1.0.dist-info/RECORD
